README.rst
setup.py
aiohttp_babel/__init__.py
aiohttp_babel/locale.py
aiohttp_babel/middlewares.py
aiohttp_babel.egg-info/PKG-INFO
aiohttp_babel.egg-info/SOURCES.txt
aiohttp_babel.egg-info/dependency_links.txt
aiohttp_babel.egg-info/requires.txt
aiohttp_babel.egg-info/top_level.txt