Metadata-Version: 1.0
Name: aiohttp-babel
Version: 0.0.3
Summary: Babel localisation support for aiohttp
Home-page: https://github.com/jie/aiohttp-babel
Author: zhouyang
Author-email: zhouyang@zhouyang.me
License: BSD
Keywords: aiohttp locale babel localisation
Platform: UNKNOWN
